[
  {
    "id": 1,
    "hostId": 500,
    "hostName": "Mike Chen",
    "hostDupr": 3.8,
    "courtId": 1,
    "courtName": "Pickleball Station",
    "datetime": "2026-03-25T18:00:00",
    "format": "doubles",
    "needed": 2,
    "joined": [{"id": 501, "name": "Lisa Wang", "dupr": 4.0}],
    "duprRange": [3.5, 4.5],
    "notes": "Bring own balls",
    "status": "open",
    "city": "Irvine"
  },
  {
    "id": 2,
    "hostId": 502,
    "hostName": "David Rodriguez",
    "hostDupr": 3.5,
    "courtId": 2,
    "courtName": "Rancho San Joaquin",
    "datetime": "2026-03-25T09:00:00",
    "format": "singles",
    "needed": 1,
    "joined": [],
    "duprRange": [3.0, 4.0],
    "notes": "Looking for a fun singles match",
    "status": "open",
    "city": "Irvine"
  },
  {
    "id": 3,
    "hostId": 503,
    "hostName": "Amy Wang",
    "hostDupr": 4.5,
    "courtId": 4,
    "courtName": "Lakeshore Athletic Club",
    "datetime": "2026-03-26T10:00:00",
    "format": "doubles",
    "needed": 3,
    "joined": [{"id": 509, "name": "Emily Clark", "dupr": 4.7}],
    "duprRange": [4.0, 5.0],
    "notes": "Indoor courts, need 3 more for doubles",
    "status": "open",
    "city": "Irvine"
  },
  {
    "id": 4,
    "hostId": 504,
    "hostName": "Chris Thompson",
    "hostDupr": 3.2,
    "courtId": 9,
    "courtName": "Newport Beach PB Courts",
    "datetime": "2026-03-26T16:00:00",
    "format": "doubles",
    "needed": 2,
    "joined": [{"id": 510, "name": "Kevin Nguyen", "dupr": 3.6}, {"id": 508, "name": "James Lee", "dupr": 3.1}],
    "duprRange": [2.5, 4.0],
    "notes": "Casual game, all levels welcome",
    "status": "open",
    "city": "Newport Beach"
  },
  {
    "id": 5,
    "hostId": 505,
    "hostName": "Nicole Kim",
    "hostDupr": 4.0,
    "courtId": 8,
    "courtName": "Costa Mesa Pickleball",
    "datetime": "2026-03-27T19:00:00",
    "format": "mixed",
    "needed": 2,
    "joined": [{"id": 506, "name": "Ryan Patel", "dupr": 3.9}],
    "duprRange": [3.5, 4.5],
    "notes": "Mixed doubles, need 1 more pair",
    "status": "open",
    "city": "Costa Mesa"
  },
  {
    "id": 6,
    "hostId": 507,
    "hostName": "Sarah Mitchell",
    "hostDupr": 4.3,
    "courtId": 11,
    "courtName": "Laguna Niguel Regional Park",
    "datetime": "2026-03-28T08:00:00",
    "format": "doubles",
    "needed": 1,
    "joined": [],
    "duprRange": [4.0, 5.0],
    "notes": "Morning doubles, early bird!",
    "status": "open",
    "city": "Laguna Niguel"
  },
  {
    "id": 7,
    "hostId": 511,
    "hostName": "Megan Davis",
    "hostDupr": 4.1,
    "courtId": 15,
    "courtName": "Santa Monica Pickleball Club",
    "datetime": "2026-03-28T14:00:00",
    "format": "singles",
    "needed": 1,
    "joined": [],
    "duprRange": [3.5, 4.5],
    "notes": "Singles match by the beach",
    "status": "open",
    "city": "Santa Monica"
  },
  {
    "id": 8,
    "hostId": 513,
    "hostName": "Amanda Garcia",
    "hostDupr": 4.4,
    "courtId": 12,
    "courtName": "Anaheim Pickleball Center",
    "datetime": "2026-03-29T11:00:00",
    "format": "doubles",
    "needed": 3,
    "joined": [{"id": 515, "name": "Rachel Adams", "dupr": 4.6}],
    "duprRange": [4.0, 5.0],
    "notes": "Competitive doubles, reserve courts booked",
    "status": "open",
    "city": "Anaheim"
  },
  {
    "id": 9,
    "hostId": 514,
    "hostName": "Brandon Scott",
    "hostDupr": 3.7,
    "courtId": 6,
    "courtName": "Glen IR Pickleball Complex",
    "datetime": "2026-03-29T17:00:00",
    "format": "doubles",
    "needed": 2,
    "joined": [{"id": 518, "name": "Jason Brown", "dupr": 3.8}, {"id": 516, "name": "Daniel Kim", "dupr": 3.3}],
    "duprRange": [3.0, 4.0],
    "notes": "After-work doubles, drinks after!",
    "status": "open",
    "city": "Irvine"
  },
  {
    "id": 10,
    "hostId": 517,
    "hostName": "Lauren Taylor",
    "hostDupr": 4.0,
    "courtId": 28,
    "courtName": "Long Beach Pickleball Hub",
    "datetime": "2026-03-30T10:00:00",
    "format": "mixed",
    "needed": 1,
    "joined": [],
    "duprRange": [3.5, 4.5],
    "notes": "Mixed doubles partner needed",
    "status": "open",
    "city": "Long Beach"
  }
]
